code_wake_sql13_store/__init__.py
code_wake_sql13_store/pkg_meta.py
code_wake_sql13_store/sql13store.py
code_wake_sql13_store/utils.py
code_wake_sql13_store-0.3.3.dist-info/LICENSE
code_wake_sql13_store-0.3.3.dist-info/METADATA
code_wake_sql13_store-0.3.3.dist-info/WHEEL
code_wake_sql13_store-0.3.3.dist-info/entry_points.txt
code_wake_sql13_store-0.3.3.dist-info/top_level.txt
code_wake_sql13_store-0.3.3.dist-info/RECORD
