Metadata-Version: 2.1
Name: code-wake-sql13-store
Version: 0.3.3
Summary: Code Wake SQL Academy 1.3 store adapter
Home-page: https://github.com/mwri/pycodewake-sql13-store
Author: Michael Wright
Author-email: mjw@methodanalysis.com
License: UNKNOWN
Platform: UNKNOWN
Classifier: Programming Language :: Python :: 3
Classifier: License :: OSI Approved :: MIT License
Classifier: Operating System :: OS Independent
Requires-Python: >=3.6
Requires-Dist: bencode.py (~=4.0.0)
Requires-Dist: code-wake (~=0.2.0)
Requires-Dist: sqlalchemy-utils (>=0.36.0)
Requires-Dist: sqlalchemy (<1.4.0)
Provides-Extra: dev
Requires-Dist: black (==22.3.0) ; extra == 'dev'
Requires-Dist: coverage (==6.2) ; extra == 'dev'
Requires-Dist: isort (==5.10.1) ; extra == 'dev'
Requires-Dist: mypy (==0.961) ; extra == 'dev'
Requires-Dist: pytest (==7.0.1) ; extra == 'dev'
Requires-Dist: types-sqlalchemy-utils (==1.0.0) ; extra == 'dev'
Requires-Dist: types-sqlalchemy (==1.4.41) ; extra == 'dev'
